todoi_cli/__init__.py
todoi_cli/auth.py
todoi_cli/checkconfig.py
todoi_cli/labelcontroller.py
todoi_cli/listcontroller.py
todoi_cli/main.py
todoi_cli/projectcontroller.py
todoi_cli/synctodoist.py
todoi_cli/taskcontroller.py
todoi_cli/togglcontroller.py
todoicli-1.0.8.dist-info/METADATA
todoicli-1.0.8.dist-info/RECORD
todoicli-1.0.8.dist-info/WHEEL
todoicli-1.0.8.dist-info/entry_points.txt
todoicli-1.0.8.dist-info/top_level.txt
